[{"ScientificName":"Clinker","EnglishName":null,"Biomass_Kg_Km2":"5.039","Classification":"Marine litter"},{"ScientificName":"Fishing gear","EnglishName":null,"Biomass_Kg_Km2":"0.118","Classification":"Marine litter"},{"ScientificName":"Marine organic","EnglishName":"Marine organic","Biomass_Kg_Km2":"3.556","Classification":"Natural debris"},{"ScientificName":"Marine plants","EnglishName":"Marine plants","Biomass_Kg_Km2":"0.446","Classification":"Natural debris"},{"ScientificName":"Plastic","EnglishName":null,"Biomass_Kg_Km2":"2.001","Classification":"Marine litter"},{"ScientificName":"Scyliorhinus canicula eggs","EnglishName":null,"Biomass_Kg_Km2":"0.093","Classification":"Discarded"},{"ScientificName":"Shells","EnglishName":"Shells","Biomass_Kg_Km2":"1.712","Classification":"Natural debris"},{"ScientificName":"Terrestrial plants","EnglishName":"Terrestrial plants","Biomass_Kg_Km2":"3.376","Classification":"Natural debris"},{"ScientificName":"Textiles","EnglishName":null,"Biomass_Kg_Km2":"0.105","Classification":"Marine litter"},{"ScientificName":"Unclassified waste","EnglishName":null,"Biomass_Kg_Km2":"0.482","Classification":"Marine litter"},{"ScientificName":"Wet wipes","EnglishName":null,"Biomass_Kg_Km2":"4.280","Classification":"Marine litter"},{"ScientificName":"Wood","EnglishName":null,"Biomass_Kg_Km2":"1.658","Classification":"Marine litter"},{"ScientificName":"Abralia veranyi","EnglishName":null,"Biomass_Kg_Km2":"0.012","Classification":"Discarded"},{"ScientificName":"Actinia sp. 2","EnglishName":null,"Biomass_Kg_Km2":"0.055","Classification":"Discarded"},{"ScientificName":"Ancistroteuthis lichtensteinii","EnglishName":null,"Biomass_Kg_Km2":"0.104","Classification":"Discarded"},{"ScientificName":"Aristeus antennatus","EnglishName":"Blue and red shrimp","Biomass_Kg_Km2":"0.050","Classification":"Discarded"},{"ScientificName":"Aristeus antennatus","EnglishName":"Blue and red shrimp","Biomass_Kg_Km2":"57.815","Classification":"Landed"},{"ScientificName":"Ascidia sp. 1","EnglishName":null,"Biomass_Kg_Km2":"0.030","Classification":"Discarded"},{"ScientificName":"Astrospartus mediterraneus","EnglishName":null,"Biomass_Kg_Km2":"0.086","Classification":"Discarded"},{"ScientificName":"Bathypolypus sponsalis","EnglishName":null,"Biomass_Kg_Km2":"0.533","Classification":"Discarded"},{"ScientificName":"Calliactis parasitica","EnglishName":null,"Biomass_Kg_Km2":"0.071","Classification":"Discarded"},{"ScientificName":"Carinaria spp.","EnglishName":null,"Biomass_Kg_Km2":"0.007","Classification":"Discarded"},{"ScientificName":"Cymbulia peronii","EnglishName":null,"Biomass_Kg_Km2":"0.094","Classification":"Discarded"},{"ScientificName":"Dardanus arrosor","EnglishName":null,"Biomass_Kg_Km2":"0.989","Classification":"Discarded"},{"ScientificName":"Etmopterus spinax","EnglishName":"Velvet belly","Biomass_Kg_Km2":"0.316","Classification":"Discarded"},{"ScientificName":"Gadiculus argenteus","EnglishName":null,"Biomass_Kg_Km2":"0.057","Classification":"Discarded"},{"ScientificName":"Galeus melastomus","EnglishName":"Blackmouth catshark","Biomass_Kg_Km2":"48.694","Classification":"Discarded"},{"ScientificName":"Geryon longipes","EnglishName":"Mediterranean geryon","Biomass_Kg_Km2":"5.910","Classification":"Landed"},{"ScientificName":"Hoplostethus mediterraneus","EnglishName":"Mediterranean slimehead","Biomass_Kg_Km2":"0.092","Classification":"Discarded"},{"ScientificName":"Hormathia alba","EnglishName":null,"Biomass_Kg_Km2":"0.071","Classification":"Discarded"},{"ScientificName":"Hymenocephalus italicus","EnglishName":null,"Biomass_Kg_Km2":"1.001","Classification":"Discarded"},{"ScientificName":"Lampanyctus crocodilus","EnglishName":null,"Biomass_Kg_Km2":"1.742","Classification":"Discarded"},{"ScientificName":"Lepidopus caudatus","EnglishName":"Silver scabbard fish","Biomass_Kg_Km2":"0.297","Classification":"Discarded"},{"ScientificName":"Lepidorhombus boscii","EnglishName":"Fourspotted megrim","Biomass_Kg_Km2":"0.434","Classification":"Discarded"},{"ScientificName":"Lepidorhombus boscii","EnglishName":"Fourspotted megrim","Biomass_Kg_Km2":"0.320","Classification":"Landed"},{"ScientificName":"Lophius budegassa","EnglishName":"Black-bellied angler","Biomass_Kg_Km2":"0.270","Classification":"Discarded"},{"ScientificName":"Lytocarpia myriophyllum","EnglishName":null,"Biomass_Kg_Km2":"0.008","Classification":"Discarded"},{"ScientificName":"Macropipus tuberculatus","EnglishName":null,"Biomass_Kg_Km2":"0.025","Classification":"Discarded"},{"ScientificName":"Merluccius merluccius","EnglishName":"European hake","Biomass_Kg_Km2":"3.086","Classification":"Discarded"},{"ScientificName":"Micromesistius poutassou","EnglishName":"Blue whiting","Biomass_Kg_Km2":"2.755","Classification":"Landed"},{"ScientificName":"Molpadia musculus","EnglishName":null,"Biomass_Kg_Km2":"0.017","Classification":"Discarded"},{"ScientificName":"Molva macrophthalma","EnglishName":"Blue ling","Biomass_Kg_Km2":"0.455","Classification":"Discarded"},{"ScientificName":"Monodaeus couchii","EnglishName":null,"Biomass_Kg_Km2":"0.004","Classification":"Discarded"},{"ScientificName":"Munida perarmata","EnglishName":null,"Biomass_Kg_Km2":"0.011","Classification":"Discarded"},{"ScientificName":"Nephrops norvegicus","EnglishName":"Norway lobster","Biomass_Kg_Km2":"4.424","Classification":"Landed"},{"ScientificName":"Nezumia aequalis","EnglishName":null,"Biomass_Kg_Km2":"1.501","Classification":"Discarded"},{"ScientificName":"Notoscopelus elongatus","EnglishName":null,"Biomass_Kg_Km2":"0.452","Classification":"Discarded"},{"ScientificName":"Pagurus prideaux","EnglishName":null,"Biomass_Kg_Km2":"0.036","Classification":"Discarded"},{"ScientificName":"Parapenaeus longirostris","EnglishName":"Deep-water rose shrimp","Biomass_Kg_Km2":"0.087","Classification":"Discarded"},{"ScientificName":"Pasiphaea multidentata","EnglishName":null,"Biomass_Kg_Km2":"0.868","Classification":"Discarded"},{"ScientificName":"Pasiphaea multidentata","EnglishName":null,"Biomass_Kg_Km2":"10.412","Classification":"Landed"},{"ScientificName":"Phascolion strombus","EnglishName":null,"Biomass_Kg_Km2":"0.001","Classification":"Discarded"},{"ScientificName":"Phycis blennoides","EnglishName":"Greater forkbeard","Biomass_Kg_Km2":"1.417","Classification":"Discarded"},{"ScientificName":"Phycis blennoides","EnglishName":"Greater forkbeard","Biomass_Kg_Km2":"3.189","Classification":"Landed"},{"ScientificName":"Plesionika martia","EnglishName":null,"Biomass_Kg_Km2":"0.034","Classification":"Discarded"},{"ScientificName":"Plesionika martia","EnglishName":null,"Biomass_Kg_Km2":"8.069","Classification":"Landed"},{"ScientificName":"Polycheles typhlops","EnglishName":null,"Biomass_Kg_Km2":"1.579","Classification":"Discarded"},{"ScientificName":"Pyrosoma atlanticum","EnglishName":null,"Biomass_Kg_Km2":"0.044","Classification":"Discarded"},{"ScientificName":"Robustosergia robusta","EnglishName":null,"Biomass_Kg_Km2":"0.146","Classification":"Discarded"},{"ScientificName":"Rossia macrosoma","EnglishName":null,"Biomass_Kg_Km2":"0.039","Classification":"Discarded"},{"ScientificName":"Scyliorhinus canicula","EnglishName":"Smallspotted catshark","Biomass_Kg_Km2":"24.934","Classification":"Discarded"},{"ScientificName":"Stomias boa","EnglishName":null,"Biomass_Kg_Km2":"0.194","Classification":"Discarded"},{"ScientificName":"Synchiropus phaeton","EnglishName":null,"Biomass_Kg_Km2":"0.080","Classification":"Discarded"},{"ScientificName":"Trachyrincus scabrus","EnglishName":null,"Biomass_Kg_Km2":"0.359","Classification":"Discarded"},{"ScientificName":"Trigla lyra","EnglishName":"Piper gurnard","Biomass_Kg_Km2":"0.091","Classification":"Discarded"},{"ScientificName":"Tubs Polychaeta","EnglishName":null,"Biomass_Kg_Km2":"0.008","Classification":"Discarded"}]