[{"ScientificName":"Fishing gear","EnglishName":null,"Biomass_Kg_Km2":"0.012","Classification":"Marine litter"},{"ScientificName":"Loligo vulgaris eggs","EnglishName":null,"Biomass_Kg_Km2":"0.499","Classification":"Discarded"},{"ScientificName":"Marine algae","EnglishName":"Marine algae","Biomass_Kg_Km2":"0.141","Classification":"Natural debris"},{"ScientificName":"Marine organic","EnglishName":"Marine organic","Biomass_Kg_Km2":"1.423","Classification":"Natural debris"},{"ScientificName":"Marine plants","EnglishName":"Marine plants","Biomass_Kg_Km2":"3.827","Classification":"Natural debris"},{"ScientificName":"Plastic","EnglishName":null,"Biomass_Kg_Km2":"6.456","Classification":"Marine litter"},{"ScientificName":"Raja spp. eggs","EnglishName":null,"Biomass_Kg_Km2":"0.073","Classification":"Discarded"},{"ScientificName":"Shells","EnglishName":"Shells","Biomass_Kg_Km2":"0.823","Classification":"Natural debris"},{"ScientificName":"Terrestrial plants","EnglishName":"Terrestrial plants","Biomass_Kg_Km2":"1.047","Classification":"Natural debris"},{"ScientificName":"Textiles","EnglishName":null,"Biomass_Kg_Km2":"0.588","Classification":"Marine litter"},{"ScientificName":"Wet wipes","EnglishName":null,"Biomass_Kg_Km2":"0.112","Classification":"Marine litter"},{"ScientificName":"Aegaeon cataphractus","EnglishName":null,"Biomass_Kg_Km2":"0.010","Classification":"Discarded"},{"ScientificName":"Alcyonium palmatum","EnglishName":null,"Biomass_Kg_Km2":"0.187","Classification":"Discarded"},{"ScientificName":"Alloteuthis media","EnglishName":null,"Biomass_Kg_Km2":"0.045","Classification":"Discarded"},{"ScientificName":"Alloteuthis spp.","EnglishName":null,"Biomass_Kg_Km2":"4.113","Classification":"Landed"},{"ScientificName":"Arnoglossus imperialis","EnglishName":null,"Biomass_Kg_Km2":"0.108","Classification":"Discarded"},{"ScientificName":"Arnoglossus laterna","EnglishName":null,"Biomass_Kg_Km2":"0.011","Classification":"Discarded"},{"ScientificName":"Arnoglossus laterna","EnglishName":null,"Biomass_Kg_Km2":"0.518","Classification":"Landed"},{"ScientificName":"Ascidia mentula","EnglishName":null,"Biomass_Kg_Km2":"0.157","Classification":"Discarded"},{"ScientificName":"Ascidia sp. 2","EnglishName":null,"Biomass_Kg_Km2":"0.057","Classification":"Discarded"},{"ScientificName":"Ascidiella spp.","EnglishName":null,"Biomass_Kg_Km2":"0.261","Classification":"Discarded"},{"ScientificName":"Astropecten irregularis","EnglishName":null,"Biomass_Kg_Km2":"0.343","Classification":"Discarded"},{"ScientificName":"Blennius ocellaris","EnglishName":null,"Biomass_Kg_Km2":"0.043","Classification":"Discarded"},{"ScientificName":"Boops boops","EnglishName":"Bogue","Biomass_Kg_Km2":"0.616","Classification":"Discarded"},{"ScientificName":"Boops boops","EnglishName":"Bogue","Biomass_Kg_Km2":"11.756","Classification":"Landed"},{"ScientificName":"Calliostoma granulatum","EnglishName":null,"Biomass_Kg_Km2":"0.084","Classification":"Discarded"},{"ScientificName":"Carapus acus","EnglishName":null,"Biomass_Kg_Km2":"0.005","Classification":"Discarded"},{"ScientificName":"Cepola macrophthalma","EnglishName":"Red bandfish","Biomass_Kg_Km2":"0.258","Classification":"Landed"},{"ScientificName":"Chelidonichthys lucerna","EnglishName":"Tub gurnard","Biomass_Kg_Km2":"0.387","Classification":"Landed"},{"ScientificName":"Chlorotocus crassicornis","EnglishName":null,"Biomass_Kg_Km2":"0.009","Classification":"Discarded"},{"ScientificName":"Citharus linguatula","EnglishName":"Spotted flounder","Biomass_Kg_Km2":"1.678","Classification":"Landed"},{"ScientificName":"Deltentosteus quadrimaculatus","EnglishName":"Four-spotted goby","Biomass_Kg_Km2":"0.079","Classification":"Landed"},{"ScientificName":"Desmacidon spp.","EnglishName":null,"Biomass_Kg_Km2":"0.030","Classification":"Discarded"},{"ScientificName":"Eledone cirrhosa","EnglishName":"Horned octopus","Biomass_Kg_Km2":"38.650","Classification":"Landed"},{"ScientificName":"Eledone moschata","EnglishName":"Musky octopus","Biomass_Kg_Km2":"12.659","Classification":"Landed"},{"ScientificName":"Eutrigla gurnardus","EnglishName":"Grey gurnad","Biomass_Kg_Km2":"1.439","Classification":"Landed"},{"ScientificName":"Galeodea echinophora","EnglishName":null,"Biomass_Kg_Km2":"1.069","Classification":"Landed"},{"ScientificName":"Goneplax rhomboides","EnglishName":null,"Biomass_Kg_Km2":"0.026","Classification":"Discarded"},{"ScientificName":"Illex coindetii","EnglishName":"Broadtail squid","Biomass_Kg_Km2":"6.520","Classification":"Landed"},{"ScientificName":"Lepidotrigla dieuzeidei","EnglishName":null,"Biomass_Kg_Km2":"0.233","Classification":"Landed"},{"ScientificName":"Lesueurigobius friesii","EnglishName":null,"Biomass_Kg_Km2":"0.029","Classification":"Discarded"},{"ScientificName":"Liocarcinus depurator","EnglishName":"Blue-leg swimcrab","Biomass_Kg_Km2":"0.235","Classification":"Discarded"},{"ScientificName":"Liocarcinus depurator","EnglishName":"Blue-leg swimcrab","Biomass_Kg_Km2":"1.580","Classification":"Landed"},{"ScientificName":"Loligo vulgaris","EnglishName":"European squid","Biomass_Kg_Km2":"1.980","Classification":"Landed"},{"ScientificName":"Lophius budegassa","EnglishName":"Black-bellied angler","Biomass_Kg_Km2":"9.295","Classification":"Discarded"},{"ScientificName":"Lophius budegassa","EnglishName":"Black-bellied angler","Biomass_Kg_Km2":"21.717","Classification":"Landed"},{"ScientificName":"Lophius piscatorius","EnglishName":"Angler","Biomass_Kg_Km2":"0.530","Classification":"Landed"},{"ScientificName":"Macropodia tenuirostris","EnglishName":null,"Biomass_Kg_Km2":"0.014","Classification":"Discarded"},{"ScientificName":"Merluccius merluccius","EnglishName":"European hake","Biomass_Kg_Km2":"0.581","Classification":"Discarded"},{"ScientificName":"Merluccius merluccius","EnglishName":"European hake","Biomass_Kg_Km2":"29.668","Classification":"Landed"},{"ScientificName":"Mesothuria intestinalis","EnglishName":null,"Biomass_Kg_Km2":"1.640","Classification":"Discarded"},{"ScientificName":"Mullus barbatus","EnglishName":"Red mullet","Biomass_Kg_Km2":"7.969","Classification":"Landed"},{"ScientificName":"Mullus surmuletus","EnglishName":"Striped red mullet","Biomass_Kg_Km2":"1.416","Classification":"Landed"},{"ScientificName":"Musculus subpictus","EnglishName":null,"Biomass_Kg_Km2":"0.002","Classification":"Discarded"},{"ScientificName":"Mytilus galloprovincialis","EnglishName":null,"Biomass_Kg_Km2":"0.406","Classification":"Discarded"},{"ScientificName":"Nemertesia ramosa","EnglishName":null,"Biomass_Kg_Km2":"0.108","Classification":"Discarded"},{"ScientificName":"Nudibranqui sp. 4","EnglishName":null,"Biomass_Kg_Km2":"0.082","Classification":"Discarded"},{"ScientificName":"Pagellus bogaraveo","EnglishName":"Red seabream","Biomass_Kg_Km2":"0.949","Classification":"Landed"},{"ScientificName":"Pagurus excavatus","EnglishName":null,"Biomass_Kg_Km2":"0.048","Classification":"Discarded"},{"ScientificName":"Parapenaeus longirostris","EnglishName":"Deep-water rose shrimp","Biomass_Kg_Km2":"0.080","Classification":"Discarded"},{"ScientificName":"Parapenaeus longirostris","EnglishName":"Deep-water rose shrimp","Biomass_Kg_Km2":"12.950","Classification":"Landed"},{"ScientificName":"Pennatula phosphorea","EnglishName":null,"Biomass_Kg_Km2":"0.200","Classification":"Discarded"},{"ScientificName":"Phycis blennoides","EnglishName":"Greater forkbeard","Biomass_Kg_Km2":"0.604","Classification":"Landed"},{"ScientificName":"Pteria hirundo","EnglishName":null,"Biomass_Kg_Km2":"0.151","Classification":"Discarded"},{"ScientificName":"Rhombosepion elegans","EnglishName":"Elegant cuttlefish","Biomass_Kg_Km2":"0.198","Classification":"Landed"},{"ScientificName":"Salpa spp.","EnglishName":null,"Biomass_Kg_Km2":"0.246","Classification":"Discarded"},{"ScientificName":"Scalpellum scalpellum","EnglishName":null,"Biomass_Kg_Km2":"0.082","Classification":"Discarded"},{"ScientificName":"Scomber scombrus","EnglishName":"Atlantic mackerel","Biomass_Kg_Km2":"5.604","Classification":"Landed"},{"ScientificName":"Scorpaena notata","EnglishName":"Small red scorpion fish","Biomass_Kg_Km2":"0.257","Classification":"Landed"},{"ScientificName":"Scyliorhinus canicula","EnglishName":"Smallspotted catshark","Biomass_Kg_Km2":"0.898","Classification":"Landed"},{"ScientificName":"Serranus hepatus","EnglishName":"Brown comber","Biomass_Kg_Km2":"0.022","Classification":"Discarded"},{"ScientificName":"Serranus hepatus","EnglishName":"Brown comber","Biomass_Kg_Km2":"0.320","Classification":"Landed"},{"ScientificName":"Solenocera membranacea","EnglishName":null,"Biomass_Kg_Km2":"0.033","Classification":"Discarded"},{"ScientificName":"Spicara spp.","EnglishName":null,"Biomass_Kg_Km2":"0.272","Classification":"Discarded"},{"ScientificName":"Spicara spp.","EnglishName":null,"Biomass_Kg_Km2":"2.167","Classification":"Landed"},{"ScientificName":"Squilla mantis","EnglishName":"Spottail mantis shrimp","Biomass_Kg_Km2":"1.934","Classification":"Discarded"},{"ScientificName":"Squilla mantis","EnglishName":"Spottail mantis shrimp","Biomass_Kg_Km2":"27.763","Classification":"Landed"},{"ScientificName":"Symphurus nigrescens","EnglishName":null,"Biomass_Kg_Km2":"0.145","Classification":"Landed"},{"ScientificName":"Trachurus mediterraneus","EnglishName":"Mediterranean horse mackerel","Biomass_Kg_Km2":"0.068","Classification":"Discarded"},{"ScientificName":"Trachurus trachurus","EnglishName":"Mackerel","Biomass_Kg_Km2":"0.339","Classification":"Discarded"},{"ScientificName":"Trachurus trachurus","EnglishName":"Mackerel","Biomass_Kg_Km2":"10.904","Classification":"Landed"},{"ScientificName":"Trisopterus capelanus","EnglishName":"Poor cod","Biomass_Kg_Km2":"0.114","Classification":"Discarded"},{"ScientificName":"Trisopterus capelanus","EnglishName":"Poor cod","Biomass_Kg_Km2":"18.274","Classification":"Landed"},{"ScientificName":"Tubs Polychaeta","EnglishName":null,"Biomass_Kg_Km2":"0.046","Classification":"Discarded"},{"ScientificName":"Veretillum cynomorium","EnglishName":null,"Biomass_Kg_Km2":"0.017","Classification":"Discarded"}]