[{"ScientificName":"Marine organic","EnglishName":"Marine organic","Biomass_Kg_Km2":"19.827","Classification":"Natural debris"},{"ScientificName":"Marine plants","EnglishName":"Marine plants","Biomass_Kg_Km2":"5.148","Classification":"Natural debris"},{"ScientificName":"Plastic","EnglishName":null,"Biomass_Kg_Km2":"3.980","Classification":"Marine litter"},{"ScientificName":"Scyliorhinus canicula eggs","EnglishName":null,"Biomass_Kg_Km2":"1.059","Classification":"Discarded"},{"ScientificName":"Shells","EnglishName":"Shells","Biomass_Kg_Km2":"4.674","Classification":"Natural debris"},{"ScientificName":"Terrestrial plants","EnglishName":"Terrestrial plants","Biomass_Kg_Km2":"1.826","Classification":"Natural debris"},{"ScientificName":"Alloteuthis spp.","EnglishName":null,"Biomass_Kg_Km2":"2.081","Classification":"Discarded"},{"ScientificName":"Argentina sphyraena","EnglishName":"Argentine","Biomass_Kg_Km2":"54.041","Classification":"Discarded"},{"ScientificName":"Argentina sphyraena","EnglishName":"Argentine","Biomass_Kg_Km2":"2.711","Classification":"Landed"},{"ScientificName":"Ascidiella spp.","EnglishName":null,"Biomass_Kg_Km2":"2.446","Classification":"Discarded"},{"ScientificName":"Astropecten irregularis","EnglishName":null,"Biomass_Kg_Km2":"3.396","Classification":"Discarded"},{"ScientificName":"Blennius ocellaris","EnglishName":null,"Biomass_Kg_Km2":"2.220","Classification":"Landed"},{"ScientificName":"Callionymus maculatus","EnglishName":null,"Biomass_Kg_Km2":"3.359","Classification":"Discarded"},{"ScientificName":"Capros aper","EnglishName":"Boarfish","Biomass_Kg_Km2":"216.894","Classification":"Discarded"},{"ScientificName":"Echinus melo","EnglishName":null,"Biomass_Kg_Km2":"76.314","Classification":"Discarded"},{"ScientificName":"Eledone cirrhosa","EnglishName":"Horned octopus","Biomass_Kg_Km2":"62.421","Classification":"Landed"},{"ScientificName":"Eutrigla gurnardus","EnglishName":"Grey gurnad","Biomass_Kg_Km2":"1.660","Classification":"Landed"},{"ScientificName":"Illex coindetii","EnglishName":"Broadtail squid","Biomass_Kg_Km2":"27.348","Classification":"Landed"},{"ScientificName":"Latreillia elegans","EnglishName":null,"Biomass_Kg_Km2":"0.599","Classification":"Discarded"},{"ScientificName":"Lepidorhombus boscii","EnglishName":"Fourspotted megrim","Biomass_Kg_Km2":"9.065","Classification":"Landed"},{"ScientificName":"Lepidotrigla cavillone","EnglishName":"Large-scaled gurnard","Biomass_Kg_Km2":"10.224","Classification":"Discarded"},{"ScientificName":"Lepidotrigla cavillone","EnglishName":"Large-scaled gurnard","Biomass_Kg_Km2":"16.524","Classification":"Landed"},{"ScientificName":"Lepidotrigla dieuzeidei","EnglishName":null,"Biomass_Kg_Km2":"4.272","Classification":"Discarded"},{"ScientificName":"Lepidotrigla dieuzeidei","EnglishName":null,"Biomass_Kg_Km2":"3.298","Classification":"Landed"},{"ScientificName":"Leptometra phalangium","EnglishName":null,"Biomass_Kg_Km2":"1435.369","Classification":"Discarded"},{"ScientificName":"Lophius budegassa","EnglishName":"Black-bellied angler","Biomass_Kg_Km2":"48.727","Classification":"Landed"},{"ScientificName":"Lophogaster typicus","EnglishName":null,"Biomass_Kg_Km2":"0.037","Classification":"Discarded"},{"ScientificName":"Lytocarpia myriophyllum","EnglishName":null,"Biomass_Kg_Km2":"0.183","Classification":"Discarded"},{"ScientificName":"Macropipus tuberculatus","EnglishName":null,"Biomass_Kg_Km2":"3.118","Classification":"Discarded"},{"ScientificName":"Macropipus tuberculatus","EnglishName":null,"Biomass_Kg_Km2":"0.303","Classification":"Landed"},{"ScientificName":"Macroramphosus scolopax","EnglishName":"Longspine spinefish","Biomass_Kg_Km2":"439.995","Classification":"Discarded"},{"ScientificName":"Merluccius merluccius","EnglishName":"European hake","Biomass_Kg_Km2":"44.438","Classification":"Discarded"},{"ScientificName":"Merluccius merluccius","EnglishName":"European hake","Biomass_Kg_Km2":"65.835","Classification":"Landed"},{"ScientificName":"Molva macrophthalma","EnglishName":"Blue ling","Biomass_Kg_Km2":"0.480","Classification":"Landed"},{"ScientificName":"Mullus barbatus","EnglishName":"Red mullet","Biomass_Kg_Km2":"12.050","Classification":"Discarded"},{"ScientificName":"Mullus barbatus","EnglishName":"Red mullet","Biomass_Kg_Km2":"142.902","Classification":"Landed"},{"ScientificName":"Ophiura ophiura","EnglishName":null,"Biomass_Kg_Km2":"3.469","Classification":"Discarded"},{"ScientificName":"Ous gasteropodes","EnglishName":null,"Biomass_Kg_Km2":"1.022","Classification":"Discarded"},{"ScientificName":"Parapenaeus longirostris","EnglishName":"Deep-water rose shrimp","Biomass_Kg_Km2":"13.291","Classification":"Discarded"},{"ScientificName":"Parapenaeus longirostris","EnglishName":"Deep-water rose shrimp","Biomass_Kg_Km2":"4.108","Classification":"Landed"},{"ScientificName":"Parastichopus regalis","EnglishName":"Royal cucumber","Biomass_Kg_Km2":"11.179","Classification":"Landed"},{"ScientificName":"Pennatula phosphorea","EnglishName":null,"Biomass_Kg_Km2":"3.396","Classification":"Discarded"},{"ScientificName":"Phycis blennoides","EnglishName":"Greater forkbeard","Biomass_Kg_Km2":"0.865","Classification":"Landed"},{"ScientificName":"Plesionika heterocarpus","EnglishName":"Arrow shrimp","Biomass_Kg_Km2":"532.375","Classification":"Discarded"},{"ScientificName":"Plesionika heterocarpus","EnglishName":"Arrow shrimp","Biomass_Kg_Km2":"0.346","Classification":"Landed"},{"ScientificName":"Pyrosoma atlanticum","EnglishName":null,"Biomass_Kg_Km2":"0.402","Classification":"Discarded"},{"ScientificName":"Rhombosepion orbignyanum","EnglishName":null,"Biomass_Kg_Km2":"8.063","Classification":"Landed"},{"ScientificName":"Scaphander lignarius","EnglishName":null,"Biomass_Kg_Km2":"0.621","Classification":"Discarded"},{"ScientificName":"Scomber scombrus","EnglishName":"Atlantic mackerel","Biomass_Kg_Km2":"1.562","Classification":"Landed"},{"ScientificName":"Serranus hepatus","EnglishName":"Brown comber","Biomass_Kg_Km2":"21.288","Classification":"Discarded"},{"ScientificName":"Serranus hepatus","EnglishName":"Brown comber","Biomass_Kg_Km2":"36.524","Classification":"Landed"},{"ScientificName":"Solenocera membranacea","EnglishName":null,"Biomass_Kg_Km2":"0.548","Classification":"Discarded"},{"ScientificName":"Trachurus trachurus","EnglishName":"Mackerel","Biomass_Kg_Km2":"15.811","Classification":"Discarded"},{"ScientificName":"Trachurus trachurus","EnglishName":"Mackerel","Biomass_Kg_Km2":"465.504","Classification":"Landed"},{"ScientificName":"Trigla lyra","EnglishName":"Piper gurnard","Biomass_Kg_Km2":"12.929","Classification":"Landed"},{"ScientificName":"Trisopterus capelanus","EnglishName":"Poor cod","Biomass_Kg_Km2":"39.800","Classification":"Discarded"},{"ScientificName":"Trisopterus capelanus","EnglishName":"Poor cod","Biomass_Kg_Km2":"36.317","Classification":"Landed"}]