[{"ScientificName":"Engraulis encrasicolus","EnglishName":"European anchovy","Biomass_T":"421.3000000000000000","Classification":"Target"},{"ScientificName":"Illex coindetii","EnglishName":"Broadtail squid","Biomass_T":"3.4000000000000000","Classification":"Discarded"},{"ScientificName":"Mola mola","EnglishName":"Ocean sunfish","Biomass_T":"1.6317700000000000","Classification":"Discarded"},{"ScientificName":"Pelagia noctiluca","EnglishName":null,"Biomass_T":"11.0610000000000000","Classification":"Discarded"},{"ScientificName":"Sardina pilchardus","EnglishName":"European pilchard","Biomass_T":"1.6050000000000000","Classification":"Discarded"},{"ScientificName":"Scomber colias","EnglishName":"Chub mackerel","Biomass_T":"1.2250000000000000","Classification":"Discarded"},{"ScientificName":"Xiphias gladius","EnglishName":"Swordfish","Biomass_T":"16.9996900000000000","Classification":"Discarded"}]