[{"NomEspecie":"Marine organic","NomComu":"Marine organic","Biomassa":"2.263","ClassificacioCaptura":"Natural debris"},{"NomEspecie":"Shells","NomComu":"Shells","Biomassa":"0.080","ClassificacioCaptura":"Natural debris"},{"NomEspecie":"Aristaeomorpha foliacea","NomComu":"Giant red shrimp","Biomassa":"0.055","ClassificacioCaptura":"Landed"},{"NomEspecie":"Aristeus antennatus","NomComu":"Blue and red shrimp","Biomassa":"0.045","ClassificacioCaptura":"Discarded"},{"NomEspecie":"Aristeus antennatus","NomComu":"Blue and red shrimp","Biomassa":"86.306","ClassificacioCaptura":"Landed"},{"NomEspecie":"Bathypolypus sponsalis","NomComu":null,"Biomassa":"0.138","ClassificacioCaptura":"Discarded"},{"NomEspecie":"Chauliodus sloani","NomComu":null,"Biomassa":"0.807","ClassificacioCaptura":"Discarded"},{"NomEspecie":"Coelorinchus caelorhincus","NomComu":null,"Biomassa":"13.371","ClassificacioCaptura":"Discarded"},{"NomEspecie":"Galeus melastomus","NomComu":"Blackmouth catshark","Biomassa":"5.748","ClassificacioCaptura":"Discarded"},{"NomEspecie":"Histioteuthis reversa","NomComu":null,"Biomassa":"0.974","ClassificacioCaptura":"Discarded"},{"NomEspecie":"Hormathia alba","NomComu":null,"Biomassa":"0.023","ClassificacioCaptura":"Discarded"},{"NomEspecie":"Hymenocephalus italicus","NomComu":null,"Biomassa":"0.221","ClassificacioCaptura":"Discarded"},{"NomEspecie":"Illex coindetii","NomComu":"Broadtail squid","Biomassa":"2.650","ClassificacioCaptura":"Discarded"},{"NomEspecie":"Lampanyctus crocodilus","NomComu":null,"Biomassa":"0.431","ClassificacioCaptura":"Discarded"},{"NomEspecie":"Lepidopus caudatus","NomComu":"Silver scabbard fish","Biomassa":"1.470","ClassificacioCaptura":"Discarded"},{"NomEspecie":"Lepidorhombus boscii","NomComu":"Fourspotted megrim","Biomassa":"0.063","ClassificacioCaptura":"Discarded"},{"NomEspecie":"Lepidorhombus boscii","NomComu":"Fourspotted megrim","Biomassa":"0.211","ClassificacioCaptura":"Landed"},{"NomEspecie":"Macropipus tuberculatus","NomComu":null,"Biomassa":"0.045","ClassificacioCaptura":"Discarded"},{"NomEspecie":"Macropodia tenuirostris","NomComu":null,"Biomassa":"0.012","ClassificacioCaptura":"Discarded"},{"NomEspecie":"Micromesistius poutassou","NomComu":"Blue whiting","Biomassa":"3.261","ClassificacioCaptura":"Landed"},{"NomEspecie":"Monodaeus couchii","NomComu":null,"Biomassa":"0.007","ClassificacioCaptura":"Discarded"},{"NomEspecie":"Munida speciosa","NomComu":null,"Biomassa":"0.112","ClassificacioCaptura":"Discarded"},{"NomEspecie":"Nephrops norvegicus","NomComu":"Norway lobster","Biomassa":"0.069","ClassificacioCaptura":"Discarded"},{"NomEspecie":"Nezumia aequalis","NomComu":null,"Biomassa":"5.302","ClassificacioCaptura":"Discarded"},{"NomEspecie":"Notoscopelus elongatus","NomComu":null,"Biomassa":"0.111","ClassificacioCaptura":"Discarded"},{"NomEspecie":"Pagurus alatus","NomComu":null,"Biomassa":"0.060","ClassificacioCaptura":"Discarded"},{"NomEspecie":"Pasiphaea multidentata","NomComu":null,"Biomassa":"0.166","ClassificacioCaptura":"Discarded"},{"NomEspecie":"Pasiphaea multidentata","NomComu":null,"Biomassa":"2.155","ClassificacioCaptura":"Landed"},{"NomEspecie":"Pasiphaea sivado","NomComu":null,"Biomassa":"0.009","ClassificacioCaptura":"Discarded"},{"NomEspecie":"Phycis blennoides","NomComu":"Greater forkbeard","Biomassa":"0.628","ClassificacioCaptura":"Discarded"},{"NomEspecie":"Phycis blennoides","NomComu":"Greater forkbeard","Biomassa":"6.582","ClassificacioCaptura":"Landed"},{"NomEspecie":"Plesionika heterocarpus","NomComu":"Arrow shrimp","Biomassa":"0.039","ClassificacioCaptura":"Discarded"},{"NomEspecie":"Plesionika martia","NomComu":null,"Biomassa":"0.178","ClassificacioCaptura":"Discarded"},{"NomEspecie":"Plesionika martia","NomComu":null,"Biomassa":"0.472","ClassificacioCaptura":"Landed"},{"NomEspecie":"Polycheles typhlops","NomComu":null,"Biomassa":"0.231","ClassificacioCaptura":"Discarded"},{"NomEspecie":"Robustosergia robusta","NomComu":null,"Biomassa":"0.094","ClassificacioCaptura":"Discarded"},{"NomEspecie":"Todarodes sagittatus","NomComu":"European flying squid","Biomassa":"7.849","ClassificacioCaptura":"Discarded"}]