[{"NomEspecie":"Clinker","NomComu":null,"Biomassa":"1.636","ClassificacioCaptura":"Marine litter"},{"NomEspecie":"Marine organic","NomComu":"Marine organic","Biomassa":"11.485","ClassificacioCaptura":"Natural debris"},{"NomEspecie":"Marine plants","NomComu":"Marine plants","Biomassa":"8.018","ClassificacioCaptura":"Natural debris"},{"NomEspecie":"Plastic","NomComu":null,"Biomassa":"1.817","ClassificacioCaptura":"Marine litter"},{"NomEspecie":"Raja spp. eggs","NomComu":null,"Biomassa":"1.622","ClassificacioCaptura":"Discarded"},{"NomEspecie":"Shells","NomComu":"Shells","Biomassa":"16.650","ClassificacioCaptura":"Natural debris"},{"NomEspecie":"Textiles","NomComu":null,"Biomassa":"0.401","ClassificacioCaptura":"Marine litter"},{"NomEspecie":"Wood","NomComu":null,"Biomassa":"4.457","ClassificacioCaptura":"Marine litter"},{"NomEspecie":"Actinia sp. 3","NomComu":null,"Biomassa":"0.047","ClassificacioCaptura":"Discarded"},{"NomEspecie":"Alcyonium palmatum","NomComu":null,"Biomassa":"3.467","ClassificacioCaptura":"Discarded"},{"NomEspecie":"Alloteuthis media","NomComu":null,"Biomassa":"6.370","ClassificacioCaptura":"Landed"},{"NomEspecie":"Alloteuthis spp.","NomComu":null,"Biomassa":"0.126","ClassificacioCaptura":"Discarded"},{"NomEspecie":"Antedon mediterranea","NomComu":null,"Biomassa":"0.069","ClassificacioCaptura":"Discarded"},{"NomEspecie":"Anthozoa 1","NomComu":null,"Biomassa":"0.386","ClassificacioCaptura":"Discarded"},{"NomEspecie":"Arnoglossus imperialis","NomComu":null,"Biomassa":"2.174","ClassificacioCaptura":"Discarded"},{"NomEspecie":"Arnoglossus laterna","NomComu":null,"Biomassa":"3.785","ClassificacioCaptura":"Discarded"},{"NomEspecie":"Ascidiella spp.","NomComu":null,"Biomassa":"0.686","ClassificacioCaptura":"Discarded"},{"NomEspecie":"Astropecten irregularis","NomComu":null,"Biomassa":"18.022","ClassificacioCaptura":"Discarded"},{"NomEspecie":"Blennius ocellaris","NomComu":null,"Biomassa":"1.210","ClassificacioCaptura":"Discarded"},{"NomEspecie":"Bolinus brandaris","NomComu":null,"Biomassa":"0.220","ClassificacioCaptura":"Discarded"},{"NomEspecie":"Boops boops","NomComu":"Bogue","Biomassa":"2.113","ClassificacioCaptura":"Discarded"},{"NomEspecie":"Calliostoma granulatum","NomComu":null,"Biomassa":"2.073","ClassificacioCaptura":"Discarded"},{"NomEspecie":"Cepola macrophthalma","NomComu":"Red bandfish","Biomassa":"1.184","ClassificacioCaptura":"Landed"},{"NomEspecie":"Chelidonichthys lucerna","NomComu":"Tub gurnard","Biomassa":"7.927","ClassificacioCaptura":"Landed"},{"NomEspecie":"Chelon saliens","NomComu":null,"Biomassa":"9.065","ClassificacioCaptura":"Landed"},{"NomEspecie":"Citharus linguatula","NomComu":"Spotted flounder","Biomassa":"2.553","ClassificacioCaptura":"Discarded"},{"NomEspecie":"Citharus linguatula","NomComu":"Spotted flounder","Biomassa":"16.614","ClassificacioCaptura":"Landed"},{"NomEspecie":"Dardanus arrosor","NomComu":null,"Biomassa":"1.824","ClassificacioCaptura":"Discarded"},{"NomEspecie":"Eledone cirrhosa","NomComu":"Horned octopus","Biomassa":"33.724","ClassificacioCaptura":"Landed"},{"NomEspecie":"Engraulis encrasicolus","NomComu":"European anchovy","Biomassa":"30.157","ClassificacioCaptura":"Discarded"},{"NomEspecie":"Esponja sp. 6","NomComu":null,"Biomassa":"0.112","ClassificacioCaptura":"Discarded"},{"NomEspecie":"Eutrigla gurnardus","NomComu":"Grey gurnad","Biomassa":"2.073","ClassificacioCaptura":"Discarded"},{"NomEspecie":"Eutrigla gurnardus","NomComu":"Grey gurnad","Biomassa":"5.685","ClassificacioCaptura":"Landed"},{"NomEspecie":"Galeodea echinophora","NomComu":null,"Biomassa":"2.532","ClassificacioCaptura":"Discarded"},{"NomEspecie":"Goneplax rhomboides","NomComu":null,"Biomassa":"0.163","ClassificacioCaptura":"Discarded"},{"NomEspecie":"Hormathia alba","NomComu":null,"Biomassa":"0.282","ClassificacioCaptura":"Discarded"},{"NomEspecie":"Illex coindetii","NomComu":"Broadtail squid","Biomassa":"1.795","ClassificacioCaptura":"Discarded"},{"NomEspecie":"Illex coindetii","NomComu":"Broadtail squid","Biomassa":"28.185","ClassificacioCaptura":"Landed"},{"NomEspecie":"Lepidotrigla cavillone","NomComu":"Large-scaled gurnard","Biomassa":"1.586","ClassificacioCaptura":"Discarded"},{"NomEspecie":"Lepidotrigla cavillone","NomComu":"Large-scaled gurnard","Biomassa":"5.211","ClassificacioCaptura":"Landed"},{"NomEspecie":"Liocarcinus depurator","NomComu":"Blue-leg swimcrab","Biomassa":"40.342","ClassificacioCaptura":"Discarded"},{"NomEspecie":"Liocarcinus depurator","NomComu":"Blue-leg swimcrab","Biomassa":"84.058","ClassificacioCaptura":"Landed"},{"NomEspecie":"Loligo vulgaris","NomComu":"European squid","Biomassa":"2.024","ClassificacioCaptura":"Landed"},{"NomEspecie":"Lophius budegassa","NomComu":"Black-bellied angler","Biomassa":"46.518","ClassificacioCaptura":"Discarded"},{"NomEspecie":"Lophius budegassa","NomComu":"Black-bellied angler","Biomassa":"50.923","ClassificacioCaptura":"Landed"},{"NomEspecie":"Lophius piscatorius","NomComu":"Angler","Biomassa":"9.370","ClassificacioCaptura":"Landed"},{"NomEspecie":"Macropodia tenuirostris","NomComu":null,"Biomassa":"3.467","ClassificacioCaptura":"Discarded"},{"NomEspecie":"Merluccius merluccius","NomComu":"European hake","Biomassa":"103.438","ClassificacioCaptura":"Discarded"},{"NomEspecie":"Merluccius merluccius","NomComu":"European hake","Biomassa":"246.359","ClassificacioCaptura":"Landed"},{"NomEspecie":"Mullus barbatus","NomComu":"Red mullet","Biomassa":"9.030","ClassificacioCaptura":"Landed"},{"NomEspecie":"Mullus surmuletus","NomComu":"Striped red mullet","Biomassa":"1.859","ClassificacioCaptura":"Landed"},{"NomEspecie":"Nemertesia antennina","NomComu":null,"Biomassa":"1.282","ClassificacioCaptura":"Discarded"},{"NomEspecie":"Neopycnodonte cochlear","NomComu":null,"Biomassa":"0.159","ClassificacioCaptura":"Discarded"},{"NomEspecie":"Nephrops norvegicus","NomComu":"Norway lobster","Biomassa":"2.243","ClassificacioCaptura":"Landed"},{"NomEspecie":"Pagurus excavatus","NomComu":null,"Biomassa":"1.557","ClassificacioCaptura":"Discarded"},{"NomEspecie":"Parapenaeus longirostris","NomComu":"Deep-water pink shrimp","Biomassa":"0.488","ClassificacioCaptura":"Discarded"},{"NomEspecie":"Pennatula phosphorea","NomComu":null,"Biomassa":"1.141","ClassificacioCaptura":"Discarded"},{"NomEspecie":"Pennatula rubra","NomComu":null,"Biomassa":"2.492","ClassificacioCaptura":"Discarded"},{"NomEspecie":"Pyrosoma atlanticum","NomComu":null,"Biomassa":"0.419","ClassificacioCaptura":"Discarded"},{"NomEspecie":"Raja spp.","NomComu":"Rays nei","Biomassa":"37.136","ClassificacioCaptura":"Landed"},{"NomEspecie":"Sardina pilchardus","NomComu":"European pilchard","Biomassa":"22.392","ClassificacioCaptura":"Discarded"},{"NomEspecie":"Scalpellum scalpellum","NomComu":null,"Biomassa":"0.069","ClassificacioCaptura":"Discarded"},{"NomEspecie":"Scomber scombrus","NomComu":"Atlantic mackerel","Biomassa":"0.730","ClassificacioCaptura":"Discarded"},{"NomEspecie":"Scomber scombrus","NomComu":"Atlantic mackerel","Biomassa":"9.473","ClassificacioCaptura":"Landed"},{"NomEspecie":"Sepia elegans","NomComu":"Elegant cuttlefish","Biomassa":"1.018","ClassificacioCaptura":"Discarded"},{"NomEspecie":"Sepia elegans","NomComu":"Elegant cuttlefish","Biomassa":"5.781","ClassificacioCaptura":"Landed"},{"NomEspecie":"Sepietta oweniana","NomComu":null,"Biomassa":"0.748","ClassificacioCaptura":"Discarded"},{"NomEspecie":"Serranus hepatus","NomComu":"Brown comber","Biomassa":"0.502","ClassificacioCaptura":"Discarded"},{"NomEspecie":"Serranus hepatus","NomComu":"Brown comber","Biomassa":"1.407","ClassificacioCaptura":"Landed"},{"NomEspecie":"Spicara flexuosa","NomComu":null,"Biomassa":"3.980","ClassificacioCaptura":"Discarded"},{"NomEspecie":"Squilla mantis","NomComu":"Spottail mantis shrimp","Biomassa":"2.860","ClassificacioCaptura":"Discarded"},{"NomEspecie":"Squilla mantis","NomComu":"Spottail mantis shrimp","Biomassa":"19.254","ClassificacioCaptura":"Landed"},{"NomEspecie":"Trachinus draco","NomComu":"Greater weever","Biomassa":"4.600","ClassificacioCaptura":"Landed"},{"NomEspecie":"Trachurus trachurus","NomComu":"Mackerel","Biomassa":"1.015","ClassificacioCaptura":"Discarded"},{"NomEspecie":"Trachurus trachurus","NomComu":"Mackerel","Biomassa":"12.836","ClassificacioCaptura":"Landed"},{"NomEspecie":"Trisopterus capelanus","NomComu":"Poor cod","Biomassa":"3.633","ClassificacioCaptura":"Discarded"},{"NomEspecie":"Trisopterus capelanus","NomComu":"Poor cod","Biomassa":"15.300","ClassificacioCaptura":"Landed"},{"NomEspecie":"Uranoscopus scaber","NomComu":"Stargazer","Biomassa":"3.800","ClassificacioCaptura":"Landed"},{"NomEspecie":"Venus nux","NomComu":null,"Biomassa":"6.028","ClassificacioCaptura":"Discarded"}]