[{"NomEspecie":"Clinker","NomComu":null,"Biomassa":"2.111","ClassificacioCaptura":"Marine litter"},{"NomEspecie":"Fishing gear","NomComu":null,"Biomassa":"0.005","ClassificacioCaptura":"Marine litter"},{"NomEspecie":"Gastropoda eggs","NomComu":null,"Biomassa":"0.023","ClassificacioCaptura":"Discarded"},{"NomEspecie":"Marine organic","NomComu":"Marine organic","Biomassa":"2.973","ClassificacioCaptura":"Natural debris"},{"NomEspecie":"Marine plants","NomComu":"Marine plants","Biomassa":"0.878","ClassificacioCaptura":"Natural debris"},{"NomEspecie":"Plastic","NomComu":null,"Biomassa":"0.469","ClassificacioCaptura":"Marine litter"},{"NomEspecie":"Scyliorhinus canicula eggs","NomComu":null,"Biomassa":"0.057","ClassificacioCaptura":"Discarded"},{"NomEspecie":"Shells","NomComu":"Shells","Biomassa":"0.516","ClassificacioCaptura":"Natural debris"},{"NomEspecie":"Terrestrial plants","NomComu":"Terrestrial plants","Biomassa":"2.645","ClassificacioCaptura":"Natural debris"},{"NomEspecie":"Abralia veranyi","NomComu":null,"Biomassa":"0.038","ClassificacioCaptura":"Discarded"},{"NomEspecie":"Actinauge richardi","NomComu":null,"Biomassa":"0.189","ClassificacioCaptura":"Discarded"},{"NomEspecie":"Aegaeon lacazei","NomComu":null,"Biomassa":"0.003","ClassificacioCaptura":"Discarded"},{"NomEspecie":"Alpheus glaber","NomComu":null,"Biomassa":"0.001","ClassificacioCaptura":"Discarded"},{"NomEspecie":"Argentina sphyraena","NomComu":"Argentine","Biomassa":"1.383","ClassificacioCaptura":"Landed"},{"NomEspecie":"Astropecten irregularis","NomComu":null,"Biomassa":"0.579","ClassificacioCaptura":"Discarded"},{"NomEspecie":"Bathypolypus sponsalis","NomComu":null,"Biomassa":"0.156","ClassificacioCaptura":"Discarded"},{"NomEspecie":"Chlorotocus crassicornis","NomComu":null,"Biomassa":"0.110","ClassificacioCaptura":"Discarded"},{"NomEspecie":"Coelorinchus caelorhincus","NomComu":null,"Biomassa":"0.438","ClassificacioCaptura":"Discarded"},{"NomEspecie":"Conger conger","NomComu":"European conger","Biomassa":"7.894","ClassificacioCaptura":"Landed"},{"NomEspecie":"Dardanus arrosor","NomComu":null,"Biomassa":"0.305","ClassificacioCaptura":"Discarded"},{"NomEspecie":"Eledone cirrhosa","NomComu":"Horned octopus","Biomassa":"8.129","ClassificacioCaptura":"Landed"},{"NomEspecie":"Epigonus denticulatus","NomComu":null,"Biomassa":"0.014","ClassificacioCaptura":"Discarded"},{"NomEspecie":"Gadiculus argenteus","NomComu":null,"Biomassa":"5.065","ClassificacioCaptura":"Discarded"},{"NomEspecie":"Galeus melastomus","NomComu":"Blackmouth catshark","Biomassa":"0.621","ClassificacioCaptura":"Discarded"},{"NomEspecie":"Galeus melastomus","NomComu":"Blackmouth catshark","Biomassa":"4.921","ClassificacioCaptura":"Landed"},{"NomEspecie":"Goneplax rhomboides","NomComu":null,"Biomassa":"0.013","ClassificacioCaptura":"Discarded"},{"NomEspecie":"Helicolenus dactylopterus","NomComu":"Rockfish","Biomassa":"2.742","ClassificacioCaptura":"Landed"},{"NomEspecie":"Histioteuthis reversa","NomComu":null,"Biomassa":"0.026","ClassificacioCaptura":"Discarded"},{"NomEspecie":"Hormathia alba","NomComu":null,"Biomassa":"0.022","ClassificacioCaptura":"Discarded"},{"NomEspecie":"Illex coindetii","NomComu":"Broadtail squid","Biomassa":"13.970","ClassificacioCaptura":"Landed"},{"NomEspecie":"Lampanyctus crocodilus","NomComu":null,"Biomassa":"0.046","ClassificacioCaptura":"Discarded"},{"NomEspecie":"Lepidorhombus boscii","NomComu":"Fourspotted megrim","Biomassa":"0.043","ClassificacioCaptura":"Discarded"},{"NomEspecie":"Lepidorhombus boscii","NomComu":"Fourspotted megrim","Biomassa":"7.581","ClassificacioCaptura":"Landed"},{"NomEspecie":"Liocarcinus depurator","NomComu":"Blue-leg swimcrab","Biomassa":"0.194","ClassificacioCaptura":"Landed"},{"NomEspecie":"Lophius budegassa","NomComu":"Black-bellied angler","Biomassa":"0.428","ClassificacioCaptura":"Discarded"},{"NomEspecie":"Lophius budegassa","NomComu":"Black-bellied angler","Biomassa":"9.557","ClassificacioCaptura":"Landed"},{"NomEspecie":"Macropipus tuberculatus","NomComu":null,"Biomassa":"0.209","ClassificacioCaptura":"Discarded"},{"NomEspecie":"Macropipus tuberculatus","NomComu":null,"Biomassa":"4.551","ClassificacioCaptura":"Landed"},{"NomEspecie":"Medorippe lanata","NomComu":null,"Biomassa":"0.130","ClassificacioCaptura":"Discarded"},{"NomEspecie":"Merluccius merluccius","NomComu":"European hake","Biomassa":"15.107","ClassificacioCaptura":"Discarded"},{"NomEspecie":"Merluccius merluccius","NomComu":"European hake","Biomassa":"4.368","ClassificacioCaptura":"Landed"},{"NomEspecie":"Micromesistius poutassou","NomComu":"Blue whiting","Biomassa":"70.152","ClassificacioCaptura":"Landed"},{"NomEspecie":"Molva macrophthalma","NomComu":"Blue ling","Biomassa":"6.149","ClassificacioCaptura":"Landed"},{"NomEspecie":"Monodaeus couchii","NomComu":null,"Biomassa":"0.002","ClassificacioCaptura":"Discarded"},{"NomEspecie":"Munida intermedia","NomComu":null,"Biomassa":"0.012","ClassificacioCaptura":"Landed"},{"NomEspecie":"Munida speciosa","NomComu":null,"Biomassa":"0.005","ClassificacioCaptura":"Landed"},{"NomEspecie":"Nephrops norvegicus","NomComu":"Norway lobster","Biomassa":"0.033","ClassificacioCaptura":"Discarded"},{"NomEspecie":"Nephrops norvegicus","NomComu":"Norway lobster","Biomassa":"15.394","ClassificacioCaptura":"Landed"},{"NomEspecie":"Notoscopelus elongatus","NomComu":null,"Biomassa":"0.020","ClassificacioCaptura":"Discarded"},{"NomEspecie":"Parapenaeus longirostris","NomComu":"Deep-water pink shrimp","Biomassa":"0.090","ClassificacioCaptura":"Discarded"},{"NomEspecie":"Parapenaeus longirostris","NomComu":"Deep-water pink shrimp","Biomassa":"22.134","ClassificacioCaptura":"Landed"},{"NomEspecie":"Pasiphaea sivado","NomComu":null,"Biomassa":"0.006","ClassificacioCaptura":"Discarded"},{"NomEspecie":"Phascolion strombus","NomComu":null,"Biomassa":"0.015","ClassificacioCaptura":"Discarded"},{"NomEspecie":"Phycis blennoides","NomComu":"Greater forkbeard","Biomassa":"0.598","ClassificacioCaptura":"Discarded"},{"NomEspecie":"Phycis blennoides","NomComu":"Greater forkbeard","Biomassa":"28.388","ClassificacioCaptura":"Landed"},{"NomEspecie":"Plesionika edwardsii","NomComu":"Stripped soldier shrimp","Biomassa":"21.341","ClassificacioCaptura":"Landed"},{"NomEspecie":"Plesionika gigliolii","NomComu":null,"Biomassa":"0.174","ClassificacioCaptura":"Discarded"},{"NomEspecie":"Plesionika gigliolii","NomComu":null,"Biomassa":"0.011","ClassificacioCaptura":"Landed"},{"NomEspecie":"Plesionika heterocarpus","NomComu":"Arrow shrimp","Biomassa":"0.424","ClassificacioCaptura":"Discarded"},{"NomEspecie":"Plesionika heterocarpus","NomComu":"Arrow shrimp","Biomassa":"2.212","ClassificacioCaptura":"Landed"},{"NomEspecie":"Plesionika martia","NomComu":null,"Biomassa":"0.007","ClassificacioCaptura":"Discarded"},{"NomEspecie":"Processa canaliculata","NomComu":null,"Biomassa":"0.008","ClassificacioCaptura":"Discarded"},{"NomEspecie":"Rossia macrosoma","NomComu":null,"Biomassa":"0.865","ClassificacioCaptura":"Landed"},{"NomEspecie":"Scyliorhinus canicula","NomComu":"Smallspotted catshark","Biomassa":"1.202","ClassificacioCaptura":"Discarded"},{"NomEspecie":"Scyliorhinus canicula","NomComu":"Smallspotted catshark","Biomassa":"23.696","ClassificacioCaptura":"Landed"},{"NomEspecie":"Sepietta spp.","NomComu":null,"Biomassa":"0.014","ClassificacioCaptura":"Discarded"},{"NomEspecie":"Solenocera membranacea","NomComu":null,"Biomassa":"0.023","ClassificacioCaptura":"Discarded"},{"NomEspecie":"Stomias boa","NomComu":null,"Biomassa":"0.031","ClassificacioCaptura":"Discarded"},{"NomEspecie":"Todarodes sagittatus","NomComu":"European flying squid","Biomassa":"6.967","ClassificacioCaptura":"Landed"},{"NomEspecie":"Trigla lyra","NomComu":"Piper gurnard","Biomassa":"0.038","ClassificacioCaptura":"Discarded"},{"NomEspecie":"Trigla lyra","NomComu":"Piper gurnard","Biomassa":"2.174","ClassificacioCaptura":"Landed"}]