[{"ScientificName":"Marine algae","EnglishName":"Marine algae","Biomass_Kg_Km2":"0.009","Classification":"Natural debris"},{"ScientificName":"Marine organic","EnglishName":"Marine organic","Biomass_Kg_Km2":"2.264","Classification":"Natural debris"},{"ScientificName":"Marine plants","EnglishName":"Marine plants","Biomass_Kg_Km2":"3.814","Classification":"Natural debris"},{"ScientificName":"Plastic","EnglishName":null,"Biomass_Kg_Km2":"0.431","Classification":"Marine litter"},{"ScientificName":"Raja spp. eggs","EnglishName":null,"Biomass_Kg_Km2":"0.126","Classification":"Discarded"},{"ScientificName":"Scyliorhinus canicula eggs","EnglishName":null,"Biomass_Kg_Km2":"0.057","Classification":"Discarded"},{"ScientificName":"Shells","EnglishName":"Shells","Biomass_Kg_Km2":"0.861","Classification":"Natural debris"},{"ScientificName":"Terrestrial plants","EnglishName":"Terrestrial plants","Biomass_Kg_Km2":"1.815","Classification":"Natural debris"},{"ScientificName":"Textiles","EnglishName":null,"Biomass_Kg_Km2":"1.722","Classification":"Marine litter"},{"ScientificName":"Wet wipes","EnglishName":null,"Biomass_Kg_Km2":"0.308","Classification":"Marine litter"},{"ScientificName":"Actinia sp. 2","EnglishName":null,"Biomass_Kg_Km2":"0.012","Classification":"Discarded"},{"ScientificName":"Aegaeon cataphractus","EnglishName":null,"Biomass_Kg_Km2":"0.011","Classification":"Discarded"},{"ScientificName":"Alcyonium palmatum","EnglishName":null,"Biomass_Kg_Km2":"0.055","Classification":"Discarded"},{"ScientificName":"Alloteuthis media","EnglishName":null,"Biomass_Kg_Km2":"0.033","Classification":"Discarded"},{"ScientificName":"Alloteuthis media","EnglishName":null,"Biomass_Kg_Km2":"2.486","Classification":"Landed"},{"ScientificName":"Alpheus glaber","EnglishName":null,"Biomass_Kg_Km2":"0.022","Classification":"Discarded"},{"ScientificName":"Anthozoa 1","EnglishName":null,"Biomass_Kg_Km2":"0.182","Classification":"Discarded"},{"ScientificName":"Arnoglossus laterna","EnglishName":null,"Biomass_Kg_Km2":"0.036","Classification":"Discarded"},{"ScientificName":"Arnoglossus laterna","EnglishName":null,"Biomass_Kg_Km2":"1.241","Classification":"Landed"},{"ScientificName":"Ascidiella spp.","EnglishName":null,"Biomass_Kg_Km2":"0.120","Classification":"Discarded"},{"ScientificName":"Astropecten irregularis","EnglishName":null,"Biomass_Kg_Km2":"1.569","Classification":"Discarded"},{"ScientificName":"Bolinus brandaris","EnglishName":null,"Biomass_Kg_Km2":"0.387","Classification":"Landed"},{"ScientificName":"Boops boops","EnglishName":"Bogue","Biomass_Kg_Km2":"0.236","Classification":"Discarded"},{"ScientificName":"Boops boops","EnglishName":"Bogue","Biomass_Kg_Km2":"15.815","Classification":"Landed"},{"ScientificName":"Calliostoma granulatum","EnglishName":null,"Biomass_Kg_Km2":"0.144","Classification":"Discarded"},{"ScientificName":"Citharus linguatula","EnglishName":"Spotted flounder","Biomass_Kg_Km2":"4.952","Classification":"Landed"},{"ScientificName":"Dardanus arrosor","EnglishName":null,"Biomass_Kg_Km2":"0.036","Classification":"Discarded"},{"ScientificName":"Diplodus annularis","EnglishName":"Annular seabream","Biomass_Kg_Km2":"2.553","Classification":"Landed"},{"ScientificName":"Eledone cirrhosa","EnglishName":"Horned octopus","Biomass_Kg_Km2":"4.583","Classification":"Landed"},{"ScientificName":"Engraulis encrasicolus","EnglishName":"European anchovy","Biomass_Kg_Km2":"0.757","Classification":"Discarded"},{"ScientificName":"Eutrigla gurnardus","EnglishName":"Grey gurnad","Biomass_Kg_Km2":"0.153","Classification":"Landed"},{"ScientificName":"Funiculina quadrangularis","EnglishName":null,"Biomass_Kg_Km2":"0.006","Classification":"Discarded"},{"ScientificName":"Galeodea rugosa","EnglishName":null,"Biomass_Kg_Km2":"0.889","Classification":"Landed"},{"ScientificName":"Gobius niger","EnglishName":"Black goby","Biomass_Kg_Km2":"4.966","Classification":"Landed"},{"ScientificName":"Goneplax rhomboides","EnglishName":null,"Biomass_Kg_Km2":"0.132","Classification":"Discarded"},{"ScientificName":"Holothuria forskali","EnglishName":"Cotton spinner","Biomass_Kg_Km2":"0.703","Classification":"Discarded"},{"ScientificName":"Illex coindetii","EnglishName":"Broadtail squid","Biomass_Kg_Km2":"0.365","Classification":"Discarded"},{"ScientificName":"Illex coindetii","EnglishName":"Broadtail squid","Biomass_Kg_Km2":"66.160","Classification":"Landed"},{"ScientificName":"Lepidotrigla cavillone","EnglishName":"Large-scaled gurnard","Biomass_Kg_Km2":"3.519","Classification":"Landed"},{"ScientificName":"Lesueurigobius friesii","EnglishName":null,"Biomass_Kg_Km2":"0.044","Classification":"Discarded"},{"ScientificName":"Liocarcinus depurator","EnglishName":"Blue-leg swimcrab","Biomass_Kg_Km2":"0.039","Classification":"Discarded"},{"ScientificName":"Liocarcinus depurator","EnglishName":"Blue-leg swimcrab","Biomass_Kg_Km2":"0.533","Classification":"Landed"},{"ScientificName":"Loligo vulgaris","EnglishName":"European squid","Biomass_Kg_Km2":"0.761","Classification":"Landed"},{"ScientificName":"Lophius budegassa","EnglishName":"Black-bellied angler","Biomass_Kg_Km2":"0.835","Classification":"Discarded"},{"ScientificName":"Lophius budegassa","EnglishName":"Black-bellied angler","Biomass_Kg_Km2":"4.077","Classification":"Landed"},{"ScientificName":"Lytocarpia myriophyllum","EnglishName":null,"Biomass_Kg_Km2":"0.128","Classification":"Discarded"},{"ScientificName":"Macropodia tenuirostris","EnglishName":null,"Biomass_Kg_Km2":"0.092","Classification":"Discarded"},{"ScientificName":"Medorippe lanata","EnglishName":null,"Biomass_Kg_Km2":"0.057","Classification":"Discarded"},{"ScientificName":"Merluccius merluccius","EnglishName":"European hake","Biomass_Kg_Km2":"0.183","Classification":"Discarded"},{"ScientificName":"Merluccius merluccius","EnglishName":"European hake","Biomass_Kg_Km2":"27.903","Classification":"Landed"},{"ScientificName":"Mullus barbatus","EnglishName":"Red mullet","Biomass_Kg_Km2":"12.389","Classification":"Landed"},{"ScientificName":"Mullus surmuletus","EnglishName":"Striped red mullet","Biomass_Kg_Km2":"1.405","Classification":"Landed"},{"ScientificName":"Nemertesia antennina","EnglishName":null,"Biomass_Kg_Km2":"0.049","Classification":"Discarded"},{"ScientificName":"Nemertesia ramosa","EnglishName":null,"Biomass_Kg_Km2":"0.082","Classification":"Discarded"},{"ScientificName":"Ocnus planci","EnglishName":null,"Biomass_Kg_Km2":"0.041","Classification":"Discarded"},{"ScientificName":"Octopus vulgaris","EnglishName":"Common octopus","Biomass_Kg_Km2":"2.528","Classification":"Discarded"},{"ScientificName":"Ous gasteropodes","EnglishName":null,"Biomass_Kg_Km2":"0.041","Classification":"Discarded"},{"ScientificName":"Pagellus acarne","EnglishName":"Axillary seabream","Biomass_Kg_Km2":"0.205","Classification":"Discarded"},{"ScientificName":"Pagellus acarne","EnglishName":"Axillary seabream","Biomass_Kg_Km2":"2.022","Classification":"Landed"},{"ScientificName":"Pagellus erythrinus","EnglishName":"Common pandora","Biomass_Kg_Km2":"0.559","Classification":"Discarded"},{"ScientificName":"Pagellus erythrinus","EnglishName":"Common pandora","Biomass_Kg_Km2":"31.714","Classification":"Landed"},{"ScientificName":"Parapenaeus longirostris","EnglishName":"Deep-water rose shrimp","Biomass_Kg_Km2":"0.241","Classification":"Discarded"},{"ScientificName":"Parapenaeus longirostris","EnglishName":"Deep-water rose shrimp","Biomass_Kg_Km2":"3.347","Classification":"Landed"},{"ScientificName":"Parastichopus regalis","EnglishName":"Royal cucumber","Biomass_Kg_Km2":"0.248","Classification":"Discarded"},{"ScientificName":"Pennatula phosphorea","EnglishName":null,"Biomass_Kg_Km2":"0.015","Classification":"Discarded"},{"ScientificName":"Pontobdella muricata","EnglishName":null,"Biomass_Kg_Km2":"0.009","Classification":"Discarded"},{"ScientificName":"Pteroeides griseum","EnglishName":null,"Biomass_Kg_Km2":"0.244","Classification":"Discarded"},{"ScientificName":"Salpa spp.","EnglishName":null,"Biomass_Kg_Km2":"0.049","Classification":"Discarded"},{"ScientificName":"Sardinella aurita","EnglishName":"Round sardinella","Biomass_Kg_Km2":"5.980","Classification":"Discarded"},{"ScientificName":"Scalpellum scalpellum","EnglishName":null,"Biomass_Kg_Km2":"0.036","Classification":"Discarded"},{"ScientificName":"Scomber colias","EnglishName":"Chub mackerel","Biomass_Kg_Km2":"3.175","Classification":"Landed"},{"ScientificName":"Scomber scombrus","EnglishName":"Atlantic mackerel","Biomass_Kg_Km2":"8.136","Classification":"Landed"},{"ScientificName":"Scorpaena notata","EnglishName":"Small red scorpion fish","Biomass_Kg_Km2":"0.096","Classification":"Discarded"},{"ScientificName":"Scorpaena notata","EnglishName":"Small red scorpion fish","Biomass_Kg_Km2":"0.468","Classification":"Landed"},{"ScientificName":"Sepiola spp.","EnglishName":null,"Biomass_Kg_Km2":"0.012","Classification":"Discarded"},{"ScientificName":"Serranus hepatus","EnglishName":"Brown comber","Biomass_Kg_Km2":"0.030","Classification":"Discarded"},{"ScientificName":"Serranus hepatus","EnglishName":"Brown comber","Biomass_Kg_Km2":"0.572","Classification":"Landed"},{"ScientificName":"Solenocera membranacea","EnglishName":null,"Biomass_Kg_Km2":"0.086","Classification":"Discarded"},{"ScientificName":"Spicara spp.","EnglishName":null,"Biomass_Kg_Km2":"2.822","Classification":"Landed"},{"ScientificName":"Spondyliosoma cantharus","EnglishName":"Black seabream","Biomass_Kg_Km2":"0.474","Classification":"Landed"},{"ScientificName":"Squilla mantis","EnglishName":"Spottail mantis shrimp","Biomass_Kg_Km2":"0.562","Classification":"Discarded"},{"ScientificName":"Squilla mantis","EnglishName":"Spottail mantis shrimp","Biomass_Kg_Km2":"8.516","Classification":"Landed"},{"ScientificName":"Suberites spp.","EnglishName":null,"Biomass_Kg_Km2":"0.325","Classification":"Discarded"},{"ScientificName":"Trachinus draco","EnglishName":"Greater weever","Biomass_Kg_Km2":"0.704","Classification":"Landed"},{"ScientificName":"Trachurus trachurus","EnglishName":"Mackerel","Biomass_Kg_Km2":"0.329","Classification":"Discarded"},{"ScientificName":"Trachurus trachurus","EnglishName":"Mackerel","Biomass_Kg_Km2":"10.420","Classification":"Landed"},{"ScientificName":"Trisopterus capelanus","EnglishName":"Poor cod","Biomass_Kg_Km2":"6.527","Classification":"Landed"},{"ScientificName":"Tubs Polychaeta","EnglishName":null,"Biomass_Kg_Km2":"0.008","Classification":"Discarded"},{"ScientificName":"Uranoscopus scaber","EnglishName":"Stargazer","Biomass_Kg_Km2":"0.687","Classification":"Landed"},{"ScientificName":"Venus nux","EnglishName":null,"Biomass_Kg_Km2":"0.081","Classification":"Discarded"}]