[{"NomEspecie":"Calcareous debris","NomComu":"Calcareous debris","Biomassa":"0.060","ClassificacioCaptura":"Natural debris"},{"NomEspecie":"Clinker","NomComu":null,"Biomassa":"23.069","ClassificacioCaptura":"Marine litter"},{"NomEspecie":"Fishing gear","NomComu":null,"Biomassa":"0.259","ClassificacioCaptura":"Marine litter"},{"NomEspecie":"Marine organic","NomComu":"Marine organic","Biomassa":"14.122","ClassificacioCaptura":"Natural debris"},{"NomEspecie":"Marine plants","NomComu":"Marine plants","Biomassa":"2.314","ClassificacioCaptura":"Natural debris"},{"NomEspecie":"Plastic","NomComu":null,"Biomassa":"2.611","ClassificacioCaptura":"Marine litter"},{"NomEspecie":"Raja spp. eggs","NomComu":null,"Biomassa":"0.204","ClassificacioCaptura":"Discarded"},{"NomEspecie":"Scyliorhinus canicula eggs","NomComu":null,"Biomassa":"0.182","ClassificacioCaptura":"Discarded"},{"NomEspecie":"Shells","NomComu":"Shells","Biomassa":"22.135","ClassificacioCaptura":"Natural debris"},{"NomEspecie":"Textiles","NomComu":null,"Biomassa":"0.240","ClassificacioCaptura":"Marine litter"},{"NomEspecie":"Wet wipes","NomComu":null,"Biomassa":"0.838","ClassificacioCaptura":"Marine litter"},{"NomEspecie":"Wood","NomComu":null,"Biomassa":"20.650","ClassificacioCaptura":"Marine litter"},{"NomEspecie":"Actinia sp. 2","NomComu":null,"Biomassa":"0.843","ClassificacioCaptura":"Discarded"},{"NomEspecie":"Adamsia palliata","NomComu":null,"Biomassa":"0.453","ClassificacioCaptura":"Discarded"},{"NomEspecie":"Alcyonium palmatum","NomComu":null,"Biomassa":"2.166","ClassificacioCaptura":"Discarded"},{"NomEspecie":"Anthozoa 1","NomComu":null,"Biomassa":"0.022","ClassificacioCaptura":"Discarded"},{"NomEspecie":"Aphrodita aculeata","NomComu":null,"Biomassa":"0.453","ClassificacioCaptura":"Discarded"},{"NomEspecie":"Argentina sphyraena","NomComu":"Argentine","Biomassa":"0.386","ClassificacioCaptura":"Discarded"},{"NomEspecie":"Arnoglossus laterna","NomComu":null,"Biomassa":"0.865","ClassificacioCaptura":"Discarded"},{"NomEspecie":"Ascidia mentula","NomComu":null,"Biomassa":"0.405","ClassificacioCaptura":"Discarded"},{"NomEspecie":"Ascidia sp. 2","NomComu":null,"Biomassa":"2.060","ClassificacioCaptura":"Discarded"},{"NomEspecie":"Astrospartus mediterraneus","NomComu":null,"Biomassa":"0.304","ClassificacioCaptura":"Discarded"},{"NomEspecie":"Blennius ocellaris","NomComu":null,"Biomassa":"0.362","ClassificacioCaptura":"Landed"},{"NomEspecie":"Boops boops","NomComu":"Bogue","Biomassa":"68.393","ClassificacioCaptura":"Discarded"},{"NomEspecie":"Calliactis parasitica","NomComu":null,"Biomassa":"5.476","ClassificacioCaptura":"Discarded"},{"NomEspecie":"Callionymus maculatus","NomComu":null,"Biomassa":"0.127","ClassificacioCaptura":"Discarded"},{"NomEspecie":"Calliostoma granulatum","NomComu":null,"Biomassa":"0.393","ClassificacioCaptura":"Discarded"},{"NomEspecie":"Capros aper","NomComu":"Boarfish","Biomassa":"3.090","ClassificacioCaptura":"Discarded"},{"NomEspecie":"Cepola macrophthalma","NomComu":"Red bandfish","Biomassa":"1.040","ClassificacioCaptura":"Landed"},{"NomEspecie":"Chelidonichthys cuculus","NomComu":null,"Biomassa":"2.921","ClassificacioCaptura":"Landed"},{"NomEspecie":"Citharus linguatula","NomComu":"Spotted flounder","Biomassa":"2.681","ClassificacioCaptura":"Discarded"},{"NomEspecie":"Citharus linguatula","NomComu":"Spotted flounder","Biomassa":"2.474","ClassificacioCaptura":"Landed"},{"NomEspecie":"Dardanus arrosor","NomComu":null,"Biomassa":"8.214","ClassificacioCaptura":"Discarded"},{"NomEspecie":"Eledone cirrhosa","NomComu":"Horned octopus","Biomassa":"26.670","ClassificacioCaptura":"Landed"},{"NomEspecie":"Euspira fusca","NomComu":null,"Biomassa":"0.057","ClassificacioCaptura":"Discarded"},{"NomEspecie":"Eutrigla gurnardus","NomComu":"Grey gurnad","Biomassa":"0.769","ClassificacioCaptura":"Landed"},{"NomEspecie":"Illex coindetii","NomComu":"Broadtail squid","Biomassa":"5.741","ClassificacioCaptura":"Landed"},{"NomEspecie":"Inachus dorsetensis","NomComu":null,"Biomassa":"0.002","ClassificacioCaptura":"Discarded"},{"NomEspecie":"Isopoda","NomComu":null,"Biomassa":"0.046","ClassificacioCaptura":"Discarded"},{"NomEspecie":"Lepidorhombus boscii","NomComu":"Fourspotted megrim","Biomassa":"1.409","ClassificacioCaptura":"Discarded"},{"NomEspecie":"Lepidorhombus boscii","NomComu":"Fourspotted megrim","Biomassa":"7.181","ClassificacioCaptura":"Landed"},{"NomEspecie":"Loligo vulgaris","NomComu":"European squid","Biomassa":"0.160","ClassificacioCaptura":"Landed"},{"NomEspecie":"Lophius budegassa","NomComu":"Black-bellied angler","Biomassa":"1.155","ClassificacioCaptura":"Discarded"},{"NomEspecie":"Lophius budegassa","NomComu":"Black-bellied angler","Biomassa":"32.238","ClassificacioCaptura":"Landed"},{"NomEspecie":"Lophius piscatorius","NomComu":"Angler","Biomassa":"17.970","ClassificacioCaptura":"Landed"},{"NomEspecie":"Macropipus tuberculatus","NomComu":null,"Biomassa":"0.735","ClassificacioCaptura":"Discarded"},{"NomEspecie":"Macropodia tenuirostris","NomComu":null,"Biomassa":"0.024","ClassificacioCaptura":"Discarded"},{"NomEspecie":"Merluccius merluccius","NomComu":"European hake","Biomassa":"5.015","ClassificacioCaptura":"Discarded"},{"NomEspecie":"Merluccius merluccius","NomComu":"European hake","Biomassa":"99.719","ClassificacioCaptura":"Landed"},{"NomEspecie":"Microcosmus vulgaris","NomComu":"Sand violet","Biomassa":"1.849","ClassificacioCaptura":"Discarded"},{"NomEspecie":"Mullus barbatus","NomComu":"Red mullet","Biomassa":"60.079","ClassificacioCaptura":"Landed"},{"NomEspecie":"Mullus surmuletus","NomComu":"Striped red mullet","Biomassa":"3.288","ClassificacioCaptura":"Landed"},{"NomEspecie":"Nemertesia antennina","NomComu":null,"Biomassa":"0.074","ClassificacioCaptura":"Discarded"},{"NomEspecie":"Neopycnodonte cochlear","NomComu":null,"Biomassa":"0.359","ClassificacioCaptura":"Discarded"},{"NomEspecie":"Ocnus planci","NomComu":null,"Biomassa":"1.095","ClassificacioCaptura":"Discarded"},{"NomEspecie":"Pagellus acarne","NomComu":"Axillary seabream","Biomassa":"2.429","ClassificacioCaptura":"Discarded"},{"NomEspecie":"Pagurus excavatus","NomComu":null,"Biomassa":"1.013","ClassificacioCaptura":"Discarded"},{"NomEspecie":"Pagurus prideaux","NomComu":null,"Biomassa":"1.912","ClassificacioCaptura":"Discarded"},{"NomEspecie":"Parastichopus regalis","NomComu":"Royal cucumber","Biomassa":"1.679","ClassificacioCaptura":"Discarded"},{"NomEspecie":"Phascolion strombus","NomComu":null,"Biomassa":"0.043","ClassificacioCaptura":"Discarded"},{"NomEspecie":"Phycis blennoides","NomComu":"Greater forkbeard","Biomassa":"6.518","ClassificacioCaptura":"Landed"},{"NomEspecie":"Polychaeta","NomComu":null,"Biomassa":"0.005","ClassificacioCaptura":"Discarded"},{"NomEspecie":"Pteria hirundo","NomComu":null,"Biomassa":"0.034","ClassificacioCaptura":"Discarded"},{"NomEspecie":"Rossia macrosoma","NomComu":null,"Biomassa":"0.565","ClassificacioCaptura":"Landed"},{"NomEspecie":"Scorpaena elongata","NomComu":null,"Biomassa":"3.020","ClassificacioCaptura":"Landed"},{"NomEspecie":"Scorpaena notata","NomComu":"Small red scorpion fish","Biomassa":"0.148","ClassificacioCaptura":"Landed"},{"NomEspecie":"Scyliorhinus canicula","NomComu":"Smallspotted catshark","Biomassa":"189.844","ClassificacioCaptura":"Discarded"},{"NomEspecie":"Sepia elegans","NomComu":"Elegant cuttlefish","Biomassa":"1.128","ClassificacioCaptura":"Discarded"},{"NomEspecie":"Sepia orbignyana","NomComu":null,"Biomassa":"0.601","ClassificacioCaptura":"Discarded"},{"NomEspecie":"Sepia orbignyana","NomComu":null,"Biomassa":"2.798","ClassificacioCaptura":"Landed"},{"NomEspecie":"Sepietta oweniana","NomComu":null,"Biomassa":"0.139","ClassificacioCaptura":"Discarded"},{"NomEspecie":"Serranus hepatus","NomComu":"Brown comber","Biomassa":"0.393","ClassificacioCaptura":"Discarded"},{"NomEspecie":"Spatangus purpureus","NomComu":null,"Biomassa":"4.544","ClassificacioCaptura":"Discarded"},{"NomEspecie":"Spicara flexuosa","NomComu":null,"Biomassa":"42.018","ClassificacioCaptura":"Discarded"},{"NomEspecie":"Spicara maena","NomComu":null,"Biomassa":"12.026","ClassificacioCaptura":"Discarded"},{"NomEspecie":"Spicara smaris","NomComu":"Picarel","Biomassa":"1.533","ClassificacioCaptura":"Discarded"},{"NomEspecie":"Spondyliosoma cantharus","NomComu":"Black seabream","Biomassa":"0.727","ClassificacioCaptura":"Landed"},{"NomEspecie":"Trachinus draco","NomComu":"Greater weever","Biomassa":"1.058","ClassificacioCaptura":"Landed"},{"NomEspecie":"Trachurus trachurus","NomComu":"Mackerel","Biomassa":"3.114","ClassificacioCaptura":"Discarded"},{"NomEspecie":"Trachurus trachurus","NomComu":"Mackerel","Biomassa":"62.836","ClassificacioCaptura":"Landed"},{"NomEspecie":"Trigla lyra","NomComu":"Piper gurnard","Biomassa":"1.111","ClassificacioCaptura":"Landed"},{"NomEspecie":"Trisopterus capelanus","NomComu":"Poor cod","Biomassa":"2.400","ClassificacioCaptura":"Discarded"},{"NomEspecie":"Trisopterus capelanus","NomComu":"Poor cod","Biomassa":"16.166","ClassificacioCaptura":"Landed"},{"NomEspecie":"Tubs Polychaeta","NomComu":null,"Biomassa":"0.098","ClassificacioCaptura":"Discarded"},{"NomEspecie":"Zeus faber","NomComu":"John dory","Biomassa":"7.657","ClassificacioCaptura":"Landed"}]