[{"NomEspecie":"Clinker","NomComu":null,"Biomassa":"5.010","ClassificacioCaptura":"Marine litter"},{"NomEspecie":"Marine organic","NomComu":"Marine organic","Biomassa":"9.038","ClassificacioCaptura":"Natural debris"},{"NomEspecie":"Marine plants","NomComu":"Marine plants","Biomassa":"1.090","ClassificacioCaptura":"Natural debris"},{"NomEspecie":"Metal","NomComu":null,"Biomassa":"0.154","ClassificacioCaptura":"Marine litter"},{"NomEspecie":"Plastic","NomComu":null,"Biomassa":"0.202","ClassificacioCaptura":"Marine litter"},{"NomEspecie":"Sanitary waste","NomComu":null,"Biomassa":"0.091","ClassificacioCaptura":"Marine litter"},{"NomEspecie":"Shells","NomComu":"Shells","Biomassa":"0.142","ClassificacioCaptura":"Natural debris"},{"NomEspecie":"Terrestrial plants","NomComu":"Terrestrial plants","Biomassa":"5.393","ClassificacioCaptura":"Natural debris"},{"NomEspecie":"Aristeus antennatus","NomComu":"Blue and red shrimp","Biomassa":"118.375","ClassificacioCaptura":"Landed"},{"NomEspecie":"Conger conger","NomComu":"European conger","Biomassa":"0.823","ClassificacioCaptura":"Landed"},{"NomEspecie":"Epigonus denticulatus","NomComu":null,"Biomassa":"0.505","ClassificacioCaptura":"Discarded"},{"NomEspecie":"Galeus melastomus","NomComu":"Blackmouth catshark","Biomassa":"6.096","ClassificacioCaptura":"Discarded"},{"NomEspecie":"Galeus melastomus","NomComu":"Blackmouth catshark","Biomassa":"74.556","ClassificacioCaptura":"Landed"},{"NomEspecie":"Geryon longipes","NomComu":"Mediterranean geryon","Biomassa":"17.795","ClassificacioCaptura":"Landed"},{"NomEspecie":"Helicolenus dactylopterus","NomComu":"Rockfish","Biomassa":"0.230","ClassificacioCaptura":"Landed"},{"NomEspecie":"Hoplostethus mediterraneus","NomComu":"Mediterranean slimehead","Biomassa":"2.349","ClassificacioCaptura":"Discarded"},{"NomEspecie":"Lampanyctus crocodilus","NomComu":null,"Biomassa":"0.640","ClassificacioCaptura":"Discarded"},{"NomEspecie":"Lepidopus caudatus","NomComu":"Silver scabbard fish","Biomassa":"0.784","ClassificacioCaptura":"Discarded"},{"NomEspecie":"Lepidorhombus boscii","NomComu":"Fourspotted megrim","Biomassa":"1.143","ClassificacioCaptura":"Landed"},{"NomEspecie":"Lophius piscatorius","NomComu":"Angler","Biomassa":"20.692","ClassificacioCaptura":"Landed"},{"NomEspecie":"Merluccius merluccius","NomComu":"European hake","Biomassa":"22.073","ClassificacioCaptura":"Landed"},{"NomEspecie":"Micromesistius poutassou","NomComu":"Blue whiting","Biomassa":"4.118","ClassificacioCaptura":"Landed"},{"NomEspecie":"Monodaeus couchii","NomComu":null,"Biomassa":"0.046","ClassificacioCaptura":"Discarded"},{"NomEspecie":"Mullus surmuletus","NomComu":"Striped red mullet","Biomassa":"0.571","ClassificacioCaptura":"Landed"},{"NomEspecie":"Nephrops norvegicus","NomComu":"Norway lobster","Biomassa":"6.235","ClassificacioCaptura":"Landed"},{"NomEspecie":"Nezumia aequalis","NomComu":null,"Biomassa":"0.595","ClassificacioCaptura":"Discarded"},{"NomEspecie":"Notacanthus bonaparte","NomComu":null,"Biomassa":"0.083","ClassificacioCaptura":"Discarded"},{"NomEspecie":"Parapenaeus longirostris","NomComu":"Deep-water pink shrimp","Biomassa":"0.300","ClassificacioCaptura":"Landed"},{"NomEspecie":"Paromola cuvieri","NomComu":"Paromola","Biomassa":"67.038","ClassificacioCaptura":"Landed"},{"NomEspecie":"Pasiphaea multidentata","NomComu":null,"Biomassa":"0.347","ClassificacioCaptura":"Discarded"},{"NomEspecie":"Pasiphaea multidentata","NomComu":null,"Biomassa":"6.226","ClassificacioCaptura":"Landed"},{"NomEspecie":"Phycis blennoides","NomComu":"Greater forkbeard","Biomassa":"0.209","ClassificacioCaptura":"Discarded"},{"NomEspecie":"Phycis blennoides","NomComu":"Greater forkbeard","Biomassa":"28.343","ClassificacioCaptura":"Landed"},{"NomEspecie":"Plesionika martia","NomComu":null,"Biomassa":"4.736","ClassificacioCaptura":"Landed"},{"NomEspecie":"Polycheles typhlops","NomComu":null,"Biomassa":"0.070","ClassificacioCaptura":"Discarded"},{"NomEspecie":"Polycheles typhlops","NomComu":null,"Biomassa":"0.529","ClassificacioCaptura":"Landed"},{"NomEspecie":"Rossia macrosoma","NomComu":null,"Biomassa":"0.732","ClassificacioCaptura":"Landed"},{"NomEspecie":"Scyliorhinus canicula","NomComu":"Smallspotted catshark","Biomassa":"35.732","ClassificacioCaptura":"Discarded"},{"NomEspecie":"Stomias boa","NomComu":null,"Biomassa":"0.064","ClassificacioCaptura":"Discarded"},{"NomEspecie":"Trachyrincus scabrus","NomComu":null,"Biomassa":"1.261","ClassificacioCaptura":"Discarded"}]